Metadata-Version: 1.1
Name: doujin2pdf
Version: 0.1
Summary: Doujin2pdf
Home-page: https://github.com/krypton-byte/NhentModule
Author: Krypton Byte
Author-email: galaxyvplus6434@gmail.com
License: MIT
Download-URL: https://github.com/krypton-byte/NhentModule/archive/0.0.1.tar.gz
Keywords: douji,pdf,downloader
Platform: UNKNOWN
Classifier: Development Status :: 3 - Alpha
Classifier: Intended Audience :: Developers
Classifier: Topic :: Software Development :: Build Tools
Classifier: License :: OSI Approved :: MIT License
Classifier: Programming Language :: Python :: 3.8
Classifier: Programming Language :: Python :: 3.9
